[
  {
    "name": "02_Business Flyer (Green)_3",
    "category": "Print - Flyers & Posters",
    "clean_name": "Business Flyer Green",
    "confidence": 95,
    "notes": "PSD file, name includes 'Flyer'",
    "_source_name": "02_Business Flyer (Green)_3",
    "_batch_index": 600
  },
  {
    "name": "02_Business Flyer (Green)_4",
    "category": "Print - Flyers & Posters",
    "clean_name": "Business Flyer Green",
    "confidence": 95,
    "notes": "PSD file, name includes 'Flyer'",
    "_source_name": "02_Business Flyer (Green)_4",
    "_batch_index": 601
  },
  {
    "name": "02_color_run_4x6",
    "category": "Print - Flyers & Posters",
    "clean_name": "Color Run 4x6",
    "confidence": 80,
    "notes": "PSD file, likely a flyer or print layout",
    "_source_name": "02_color_run_4x6",
    "_batch_index": 602
  },
  {
    "name": "02_Corporate Flyer Template_2",
    "category": "Print - Flyers & Posters",
    "clean_name": "Corporate Flyer Template",
    "confidence": 95,
    "notes": "PSD file, name includes 'Flyer'",
    "_source_name": "02_Corporate Flyer Template_2",
    "_batch_index": 603
  },
  {
    "name": "02_Corporate Flyer_Blue",
    "category": "Print - Flyers & Posters",
    "clean_name": "Corporate Flyer Blue",
    "confidence": 95,
    "notes": "PSD file, name includes 'Flyer'",
    "_source_name": "02_Corporate Flyer_Blue",
    "_batch_index": 604
  },
  {
    "name": "02_Corporate Flyer_Blue_2",
    "category": "Print - Flyers & Posters",
    "clean_name": "Corporate Flyer Blue",
    "confidence": 95,
    "notes": "PSD file, name includes 'Flyer'",
    "_source_name": "02_Corporate Flyer_Blue_2",
    "_batch_index": 605
  },
  {
    "name": "02_Corporate Flyer_Blue_3",
    "category": "Print - Flyers & Posters",
    "clean_name": "Corporate Flyer Blue",
    "confidence": 95,
    "notes": "PSD file, name includes 'Flyer'",
    "_source_name": "02_Corporate Flyer_Blue_3",
    "_batch_index": 606
  },
  {
    "name": "02_Corporate Flyer_Blue_4",
    "category": "Print - Flyers & Posters",
    "clean_name": "Corporate Flyer Blue",
    "confidence": 95,
    "notes": "PSD file, name includes 'Flyer'",
    "_source_name": "02_Corporate Flyer_Blue_4",
    "_batch_index": 607
  },
  {
    "name": "02_Courses",
    "category": "Print - Flyers & Posters",
    "clean_name": "Courses Flyer",
    "confidence": 75,
    "notes": "PSD file, likely a flyer for courses",
    "_source_name": "02_Courses",
    "_batch_index": 608
  },
  {
    "name": "02_Cyan Color_Flyer_3",
    "category": "Print - Flyers & Posters",
    "clean_name": "Cyan Color Flyer",
    "confidence": 95,
    "notes": "PSD file, name includes 'Flyer'",
    "_source_name": "02_Cyan Color_Flyer_3",
    "_batch_index": 609
  },
  {
    "name": "02_Cyan Color_Flyer_5",
    "category": "Print - Flyers & Posters",
    "clean_name": "Cyan Color Flyer",
    "confidence": 95,
    "notes": "PSD file, name includes 'Flyer'",
    "_source_name": "02_Cyan Color_Flyer_5",
    "_batch_index": 610
  },
  {
    "name": "02_Cyan Color_Flyer_6",
    "category": "Print - Flyers & Posters",
    "clean_name": "Cyan Color Flyer",
    "confidence": 95,
    "notes": "PSD file, name includes 'Flyer'",
    "_source_name": "02_Cyan Color_Flyer_6",
    "_batch_index": 611
  },
  {
    "name": "02_Cyan Color_Flyer_8",
    "category": "Print - Flyers & Posters",
    "clean_name": "Cyan Color Flyer",
    "confidence": 95,
    "notes": "PSD file, name includes 'Flyer'",
    "_source_name": "02_Cyan Color_Flyer_8",
    "_batch_index": 612
  },
  {
    "name": "02_design1.jpg",
    "category": "Print - Flyers & Posters",
    "clean_name": "Design 1",
    "confidence": 70,
    "notes": "PSD file, likely a print design",
    "_source_name": "02_design1.jpg",
    "_batch_index": 613
  },
  {
    "name": "02_Flyer (Dark Version)",
    "category": "Print - Flyers & Posters",
    "clean_name": "Flyer Dark Version",
    "confidence": 95,
    "notes": "PSD file, name includes 'Flyer'",
    "_source_name": "02_Flyer (Dark Version)",
    "_batch_index": 614
  },
  {
    "name": "02_Flyer (Dark Version)_2",
    "category": "Print - Flyers & Posters",
    "clean_name": "Flyer Dark Version",
    "confidence": 95,
    "notes": "PSD file, name includes 'Flyer'",
    "_source_name": "02_Flyer (Dark Version)_2",
    "_batch_index": 615
  },
  {
    "name": "02_Flyer (Dark Version)_3",
    "category": "Print - Flyers & Posters",
    "clean_name": "Flyer Dark Version",
    "confidence": 95,
    "notes": "PSD file, name includes 'Flyer'",
    "_source_name": "02_Flyer (Dark Version)_3",
    "_batch_index": 616
  },
  {
    "name": "02_Flyer (Dark Version)_4",
    "category": "Print - Flyers & Posters",
    "clean_name": "Flyer Dark Version",
    "confidence": 95,
    "notes": "PSD file, name includes 'Flyer'",
    "_source_name": "02_Flyer (Dark Version)_4",
    "_batch_index": 617
  },
  {
    "name": "02_Flyer (Dark Version)_5",
    "category": "Print - Flyers & Posters",
    "clean_name": "Flyer Dark Version",
    "confidence": 95,
    "notes": "PSD file, name includes 'Flyer'",
    "_source_name": "02_Flyer (Dark Version)_5",
    "_batch_index": 618
  },
  {
    "name": "02_Flyer (Dark Version)_6",
    "category": "Print - Flyers & Posters",
    "clean_name": "Flyer Dark Version",
    "confidence": 95,
    "notes": "PSD file, name includes 'Flyer'",
    "_source_name": "02_Flyer (Dark Version)_6",
    "_batch_index": 619
  },
  {
    "name": "02_Flyer - Red",
    "category": "Print - Flyers & Posters",
    "clean_name": "Flyer Red",
    "confidence": 95,
    "notes": "PSD file, name includes 'Flyer'",
    "_source_name": "02_Flyer - Red",
    "_batch_index": 620
  },
  {
    "name": "02_Flyer - Red_2",
    "category": "Print - Flyers & Posters",
    "clean_name": "Flyer Red",
    "confidence": 95,
    "notes": "PSD file, name includes 'Flyer'",
    "_source_name": "02_Flyer - Red_2",
    "_batch_index": 621
  },
  {
    "name": "02_Flyer - Red_3",
    "category": "Print - Flyers & Posters",
    "clean_name": "Flyer Red",
    "confidence": 95,
    "notes": "PSD file, name includes 'Flyer'",
    "_source_name": "02_Flyer - Red_3",
    "_batch_index": 622
  },
  {
    "name": "02_Flyer Design_Back Side_2",
    "category": "Print - Flyers & Posters",
    "clean_name": "Flyer Design Back Side",
    "confidence": 95,
    "notes": "PSD file, name includes 'Flyer'",
    "_source_name": "02_Flyer Design_Back Side_2",
    "_batch_index": 623
  },
  {
    "name": "02_Flyer Design_Blue Color",
    "category": "Print - Flyers & Posters",
    "clean_name": "Flyer Design Blue Color",
    "confidence": 95,
    "notes": "PSD file, name includes 'Flyer'",
    "_source_name": "02_Flyer Design_Blue Color",
    "_batch_index": 624
  },
  {
    "name": "02_Flyer Design_Blue Color_2",
    "category": "Print - Flyers & Posters",
    "clean_name": "Flyer Design Blue Color",
    "confidence": 95,
    "notes": "PSD file, name includes 'Flyer'",
    "_source_name": "02_Flyer Design_Blue Color_2",
    "_batch_index": 625
  },
  {
    "name": "02_Flyer Design_Blue Color_3",
    "category": "Print - Flyers & Posters",
    "clean_name": "Flyer Design Blue Color",
    "confidence": 95,
    "notes": "PSD file, name includes 'Flyer'",
    "_source_name": "02_Flyer Design_Blue Color_3",
    "_batch_index": 626
  },
  {
    "name": "02_Flyer Design_Blue_11",
    "category": "Print - Flyers & Posters",
    "clean_name": "Flyer Design Blue",
    "confidence": 95,
    "notes": "PSD file, name includes 'Flyer'",
    "_source_name": "02_Flyer Design_Blue_11",
    "_batch_index": 627
  },
  {
    "name": "02_Flyer Design_Blue_13",
    "category": "Print - Flyers & Posters",
    "clean_name": "Flyer Design Blue",
    "confidence": 95,
    "notes": "PSD file, name includes 'Flyer'",
    "_source_name": "02_Flyer Design_Blue_13",
    "_batch_index": 628
  },
  {
    "name": "02_Flyer Design_Blue_14",
    "category": "Print - Flyers & Posters",
    "clean_name": "Flyer Design Blue",
    "confidence": 95,
    "notes": "PSD file, name includes 'Flyer'",
    "_source_name": "02_Flyer Design_Blue_14",
    "_batch_index": 629
  },
  {
    "name": "02_Flyer Design_Blue_2",
    "category": "Print - Flyers & Posters",
    "clean_name": "Flyer Design Blue",
    "confidence": 95,
    "notes": "PSD file, name includes 'Flyer'",
    "_source_name": "02_Flyer Design_Blue_2",
    "_batch_index": 630
  },
  {
    "name": "02_Flyer Design_Blue_3",
    "category": "Print - Flyers & Posters",
    "clean_name": "Flyer Design Blue",
    "confidence": 95,
    "notes": "PSD file, name includes 'Flyer'",
    "_source_name": "02_Flyer Design_Blue_3",
    "_batch_index": 631
  },
  {
    "name": "02_Flyer Design_Blue_6",
    "category": "Print - Flyers & Posters",
    "clean_name": "Flyer Design Blue",
    "confidence": 95,
    "notes": "PSD file, name includes 'Flyer'",
    "_source_name": "02_Flyer Design_Blue_6",
    "_batch_index": 632
  },
  {
    "name": "02_Flyer Design_Blue_8",
    "category": "Print - Flyers & Posters",
    "clean_name": "Flyer Design Blue",
    "confidence": 95,
    "notes": "PSD file, name includes 'Flyer'",
    "_source_name": "02_Flyer Design_Blue_8",
    "_batch_index": 633
  },
  {
    "name": "02_Flyer Design_Blue_9",
    "category": "Print - Flyers & Posters",
    "clean_name": "Flyer Design Blue",
    "confidence": 95,
    "notes": "PSD file, name includes 'Flyer'",
    "_source_name": "02_Flyer Design_Blue_9",
    "_batch_index": 634
  },
  {
    "name": "02_Flyer Design_Colored Version",
    "category": "Print - Flyers & Posters",
    "clean_name": "Flyer Design Colored Version",
    "confidence": 95,
    "notes": "PSD file, name includes 'Flyer'",
    "_source_name": "02_Flyer Design_Colored Version",
    "_batch_index": 635
  },
  {
    "name": "02_Flyer Design_Colored Version_2",
    "category": "Print - Flyers & Posters",
    "clean_name": "Flyer Design Colored Version",
    "confidence": 95,
    "notes": "PSD file, name includes 'Flyer'",
    "_source_name": "02_Flyer Design_Colored Version_2",
    "_batch_index": 636
  },
  {
    "name": "02_Flyer Design_Colored Version_6",
    "category": "Print - Flyers & Posters",
    "clean_name": "Flyer Design Colored Version",
    "confidence": 95,
    "notes": "PSD file, name includes 'Flyer'",
    "_source_name": "02_Flyer Design_Colored Version_6",
    "_batch_index": 637
  },
  {
    "name": "02_Flyer Design_Colored Version_7",
    "category": "Print - Flyers & Posters",
    "clean_name": "Flyer Design Colored Version",
    "confidence": 95,
    "notes": "PSD file, name includes 'Flyer'",
    "_source_name": "02_Flyer Design_Colored Version_7",
    "_batch_index": 638
  },
  {
    "name": "02_Flyer Design_Dark Version",
    "category": "Print - Flyers & Posters",
    "clean_name": "Flyer Design Dark Version",
    "confidence": 95,
    "notes": "PSD file, name includes 'Flyer'",
    "_source_name": "02_Flyer Design_Dark Version",
    "_batch_index": 639
  },
  {
    "name": "02_Flyer Design_Dark version_12",
    "category": "Print - Flyers & Posters",
    "clean_name": "Flyer Design Dark Version",
    "confidence": 95,
    "notes": "PSD file, name includes 'Flyer'",
    "_source_name": "02_Flyer Design_Dark version_12",
    "_batch_index": 640
  },
  {
    "name": "02_Flyer Design_Dark version_14",
    "category": "Print - Flyers & Posters",
    "clean_name": "Flyer Design Dark Version",
    "confidence": 95,
    "notes": "PSD file, name includes 'Flyer'",
    "_source_name": "02_Flyer Design_Dark version_14",
    "_batch_index": 641
  },
  {
    "name": "02_Flyer Design_Dark version_15",
    "category": "Print - Flyers & Posters",
    "clean_name": "Flyer Design Dark Version",
    "confidence": 95,
    "notes": "PSD file, name includes 'Flyer'",
    "_source_name": "02_Flyer Design_Dark version_15",
    "_batch_index": 642
  },
  {
    "name": "02_Flyer Design_Dark Version_16",
    "category": "Print - Flyers & Posters",
    "clean_name": "Flyer Design Dark Version",
    "confidence": 95,
    "notes": "PSD file, name includes 'Flyer'",
    "_source_name": "02_Flyer Design_Dark Version_16",
    "_batch_index": 643
  },
  {
    "name": "02_Flyer Design_Dark Version_18",
    "category": "Print - Flyers & Posters",
    "clean_name": "Flyer Design Dark Version",
    "confidence": 95,
    "notes": "PSD file, name includes 'Flyer'",
    "_source_name": "02_Flyer Design_Dark Version_18",
    "_batch_index": 644
  },
  {
    "name": "02_Flyer Design_Dark Version_2",
    "category": "Print - Flyers & Posters",
    "clean_name": "Flyer Design Dark Version",
    "confidence": 95,
    "notes": "PSD file, name includes 'Flyer'",
    "_source_name": "02_Flyer Design_Dark Version_2",
    "_batch_index": 645
  },
  {
    "name": "02_Flyer Design_Dark Version_22",
    "category": "Print - Flyers & Posters",
    "clean_name": "Flyer Design Dark Version",
    "confidence": 95,
    "notes": "PSD file, name includes 'Flyer'",
    "_source_name": "02_Flyer Design_Dark Version_22",
    "_batch_index": 646
  },
  {
    "name": "02_Flyer Design_Dark Version_23",
    "category": "Print - Flyers & Posters",
    "clean_name": "Flyer Design Dark Version",
    "confidence": 95,
    "notes": "PSD file, name includes 'Flyer'",
    "_source_name": "02_Flyer Design_Dark Version_23",
    "_batch_index": 647
  },
  {
    "name": "02_Flyer Design_Dark Version_25",
    "category": "Print - Flyers & Posters",
    "clean_name": "Flyer Design Dark Version",
    "confidence": 95,
    "notes": "PSD file, name includes 'Flyer'",
    "_source_name": "02_Flyer Design_Dark Version_25",
    "_batch_index": 648
  },
  {
    "name": "02_Flyer Design_Dark version_29",
    "category": "Print - Flyers & Posters",
    "clean_name": "Flyer Design Dark Version",
    "confidence": 95,
    "notes": "PSD file, name includes 'Flyer'",
    "_source_name": "02_Flyer Design_Dark version_29",
    "_batch_index": 649
  },
  {
    "name": "02_Flyer Design_Dark Version_3",
    "category": "Print - Flyers & Posters",
    "clean_name": "Flyer Design Dark Version",
    "confidence": 95,
    "notes": "PSD file, name includes 'Flyer'",
    "_source_name": "02_Flyer Design_Dark Version_3",
    "_batch_index": 650
  },
  {
    "name": "02_Flyer Design_Dark version_31",
    "category": "Print - Flyers & Posters",
    "clean_name": "Flyer Design Dark Version",
    "confidence": 95,
    "notes": "PSD file, name includes 'Flyer'",
    "_source_name": "02_Flyer Design_Dark version_31",
    "_batch_index": 651
  },
  {
    "name": "02_Flyer Design_Dark Version_32",
    "category": "Print - Flyers & Posters",
    "clean_name": "Flyer Design Dark Version",
    "confidence": 95,
    "notes": "PSD file, name includes 'Flyer'",
    "_source_name": "02_Flyer Design_Dark Version_32",
    "_batch_index": 652
  },
  {
    "name": "02_Flyer Design_Dark Version_33",
    "category": "Print - Flyers & Posters",
    "clean_name": "Flyer Design Dark Version",
    "confidence": 95,
    "notes": "PSD file, name includes 'Flyer'",
    "_source_name": "02_Flyer Design_Dark Version_33",
    "_batch_index": 653
  },
  {
    "name": "02_Flyer Design_Dark Version_34",
    "category": "Print - Flyers & Posters",
    "clean_name": "Flyer Design Dark Version",
    "confidence": 95,
    "notes": "PSD file, name includes 'Flyer'",
    "_source_name": "02_Flyer Design_Dark Version_34",
    "_batch_index": 654
  },
  {
    "name": "02_Flyer Design_Dark Version_4",
    "category": "Print - Flyers & Posters",
    "clean_name": "Flyer Design Dark Version",
    "confidence": 95,
    "notes": "PSD file, name includes 'Flyer'",
    "_source_name": "02_Flyer Design_Dark Version_4",
    "_batch_index": 655
  },
  {
    "name": "02_Flyer Design_Dark Version_5",
    "category": "Print - Flyers & Posters",
    "clean_name": "Flyer Design Dark Version",
    "confidence": 95,
    "notes": "PSD file, name includes 'Flyer'",
    "_source_name": "02_Flyer Design_Dark Version_5",
    "_batch_index": 656
  },
  {
    "name": "02_Flyer Design_Dark Version_6",
    "category": "Print - Flyers & Posters",
    "clean_name": "Flyer Design Dark Version",
    "confidence": 95,
    "notes": "PSD file, name includes 'Flyer'",
    "_source_name": "02_Flyer Design_Dark Version_6",
    "_batch_index": 657
  },
  {
    "name": "02_Flyer Design_Dark Version_7",
    "category": "Print - Flyers & Posters",
    "clean_name": "Flyer Design Dark Version",
    "confidence": 95,
    "notes": "PSD file, name includes 'Flyer'",
    "_source_name": "02_Flyer Design_Dark Version_7",
    "_batch_index": 658
  },
  {
    "name": "02_Flyer Design_Dark Versions",
    "category": "Print - Flyers & Posters",
    "clean_name": "Flyer Design Dark Versions",
    "confidence": 95,
    "notes": "PSD file, name includes 'Flyer'",
    "_source_name": "02_Flyer Design_Dark Versions",
    "_batch_index": 659
  }
]